HISTORY.rst
LICENSE
MANIFEST.in
README.rst
setup.py
async_gui/__init__.py
async_gui/compat.py
async_gui/engine.py
async_gui/gevent_tasks.py
async_gui/tasks.py
async_gui.egg-info/PKG-INFO
async_gui.egg-info/SOURCES.txt
async_gui.egg-info/dependency_links.txt
async_gui.egg-info/requires.txt
async_gui.egg-info/top_level.txt
async_gui/toolkits/__init__.py
async_gui/toolkits/_qt.py
async_gui/toolkits/pygtk.py
async_gui/toolkits/pyqt.py
async_gui/toolkits/pyside.py
async_gui/toolkits/tk.py
async_gui/toolkits/wx.py
docs/Makefile
docs/conf.py
docs/index.rst
docs/make.bat
docs/_static/.empty
docs/_templates/.empty
examples/__init__.py
examples/cpu_work.py
examples/gtk_app.py
examples/qt_app.py
examples/qt_app_unordered_gen.py
examples/tk_app.py
examples/wx_app.py
tests/__init__.py
tests/test_engine.py
tests/test_gevent.py
tests/test_toolkits.py